AUTHORS.rst
CONTRIBUTING.rst
HISTORY.rst
LICENSE
MANIFEST.in
README.rst
setup.cfg
setup.py
django_impala_backend/__init__.py
django_impala_backend/base.py
django_impala_backend/client.py
django_impala_backend/compiler.py
django_impala_backend/creation.py
django_impala_backend/features.py
django_impala_backend/introspection.py
django_impala_backend/operations.py
django_impala_backend/schema.py
django_impala_backend/validation.py
django_impala_backend.egg-info/PKG-INFO
django_impala_backend.egg-info/SOURCES.txt
django_impala_backend.egg-info/dependency_links.txt
django_impala_backend.egg-info/not-zip-safe
django_impala_backend.egg-info/top_level.txt
docs/Makefile
docs/authors.rst
docs/conf.py
docs/contributing.rst
docs/history.rst
docs/index.rst
docs/installation.rst
docs/make.bat
docs/readme.rst
docs/usage.rst
tests/__init__.py
tests/test_django_impala_backend.py