Metadata-Version: 1.2
Name: django-impala-backend
Version: 0.1.4
Summary: use impala as django database backend
Home-page: https://github.com/drinksss/django-impala-backend
Author: drinksss
Author-email: me@drinks.ink
License: MIT license
Keywords: django_impala_backend
Platform: UNKNOWN
Classifier: Development Status :: 2 - Pre-Alpha
Classifier: Intended Audience :: Developers
Classifier: License :: OSI Approved :: MIT License
Classifier: Natural Language :: English
Classifier: Programming Language :: Python :: 3
Classifier: Programming Language :: Python :: 3.5
Classifier: Programming Language :: Python :: 3.6
Classifier: Programming Language :: Python :: 3.7
Classifier: Programming Language :: Python :: 3.8
Requires-Python: >=3.5
